{
  "id": "c1b39fc9-51c7-46be-bf40-e7abdff4a2e6",
  "prevId": "10825616-6a6c-4b63-9058-32ca2c0a5fd8",
  "version": "7",
  "dialect": "postgresql",
  "tables": {
    "public.comments": {
      "name": "comments",
      "schema": "",
      "columns": {
        "id": {
          "name": "id",
          "type": "text",
          "primaryKey": true,
          "notNull": true
        },
        "created_at": {
          "name": "created_at",
          "type": "timestamp (6) with time zone",
          "primaryKey": false,
          "notNull": true,
          "default": "now()"
        },
        "updated_at": {
          "name": "updated_at",
          "type": "timestamp (6) with time zone",
          "primaryKey": false,
          "notNull": true,
          "default": "now()"
        },
        "issue_id": {
          "name": "issue_id",
          "type": "text",
          "primaryKey": false,
          "notNull": true
        },
        "node_id": {
          "name": "node_id",
          "type": "text",
          "primaryKey": false,
          "notNull": true
        },
        "author": {
          "name": "author",
          "type": "jsonb",
          "primaryKey": false,
          "notNull": false
        },
        "body": {
          "name": "body",
          "type": "text",
          "primaryKey": false,
          "notNull": true
        },
        "comment_created_at": {
          "name": "comment_created_at",
          "type": "timestamp (6) with time zone",
          "primaryKey": false,
          "notNull": true
        },
        "comment_updated_at": {
          "name": "comment_updated_at",
          "type": "timestamp (6) with time zone",
          "primaryKey": false,
          "notNull": true
        }
      },
      "indexes": {
        "issue_id_idx": {
          "name": "issue_id_idx",
          "columns": [
            {
              "expression": "issue_id",
              "isExpression": false,
              "asc": true,
              "nulls": "last"
            }
          ],
          "isUnique": false,
          "concurrently": false,
          "method": "btree",
          "with": {}
        }
      },
      "foreignKeys": {
        "comments_issue_id_issues_id_fk": {
          "name": "comments_issue_id_issues_id_fk",
          "tableFrom": "comments",
          "tableTo": "issues",
          "columnsFrom": [
            "issue_id"
          ],
          "columnsTo": [
            "id"
          ],
          "onDelete": "no action",
          "onUpdate": "no action"
        }
      },
      "compositePrimaryKeys": {},
      "uniqueConstraints": {
        "comments_node_id_unique": {
          "name": "comments_node_id_unique",
          "nullsNotDistinct": false,
          "columns": [
            "node_id"
          ]
        }
      }
    },
    "public.installations_to_repos": {
      "name": "installations_to_repos",
      "schema": "",
      "columns": {
        "created_at": {
          "name": "created_at",
          "type": "timestamp (6) with time zone",
          "primaryKey": false,
          "notNull": true,
          "default": "now()"
        },
        "updated_at": {
          "name": "updated_at",
          "type": "timestamp (6) with time zone",
          "primaryKey": false,
          "notNull": true,
          "default": "now()"
        },
        "installation_id": {
          "name": "installation_id",
          "type": "text",
          "primaryKey": false,
          "notNull": true
        },
        "github_repo_id": {
          "name": "github_repo_id",
          "type": "bigint",
          "primaryKey": false,
          "notNull": true
        },
        "repo_node_id": {
          "name": "repo_node_id",
          "type": "text",
          "primaryKey": false,
          "notNull": true
        },
        "repo_id": {
          "name": "repo_id",
          "type": "text",
          "primaryKey": false,
          "notNull": false
        },
        "metadata": {
          "name": "metadata",
          "type": "jsonb",
          "primaryKey": false,
          "notNull": false
        },
        "added_at": {
          "name": "added_at",
          "type": "timestamp (6) with time zone",
          "primaryKey": false,
          "notNull": true
        },
        "removed_at": {
          "name": "removed_at",
          "type": "timestamp (6) with time zone",
          "primaryKey": false,
          "notNull": false
        }
      },
      "indexes": {
        "installations_to_repos_installation_idx": {
          "name": "installations_to_repos_installation_idx",
          "columns": [
            {
              "expression": "installation_id",
              "isExpression": false,
              "asc": true,
              "nulls": "last"
            }
          ],
          "isUnique": false,
          "concurrently": false,
          "method": "btree",
          "with": {}
        },
        "installations_to_repos_repo_idx": {
          "name": "installations_to_repos_repo_idx",
          "columns": [
            {
              "expression": "repo_id",
              "isExpression": false,
              "asc": true,
              "nulls": "last"
            }
          ],
          "isUnique": false,
          "concurrently": false,
          "method": "btree",
          "with": {}
        },
        "installations_to_repos_repo_node_idx": {
          "name": "installations_to_repos_repo_node_idx",
          "columns": [
            {
              "expression": "repo_node_id",
              "isExpression": false,
              "asc": true,
              "nulls": "last"
            }
          ],
          "isUnique": false,
          "concurrently": false,
          "method": "btree",
          "with": {}
        },
        "installations_to_repos_active_idx": {
          "name": "installations_to_repos_active_idx",
          "columns": [
            {
              "expression": "installation_id",
              "isExpression": false,
              "asc": true,
              "nulls": "last"
            }
          ],
          "isUnique": false,
          "where": "\"installations_to_repos\".\"removed_at\" IS NULL",
          "concurrently": false,
          "method": "btree",
          "with": {}
        }
      },
      "foreignKeys": {
        "installations_to_repos_installation_id_installations_id_fk": {
          "name": "installations_to_repos_installation_id_installations_id_fk",
          "tableFrom": "installations_to_repos",
          "tableTo": "installations",
          "columnsFrom": [
            "installation_id"
          ],
          "columnsTo": [
            "id"
          ],
          "onDelete": "no action",
          "onUpdate": "no action"
        },
        "installations_to_repos_repo_id_repos_id_fk": {
          "name": "installations_to_repos_repo_id_repos_id_fk",
          "tableFrom": "installations_to_repos",
          "tableTo": "repos",
          "columnsFrom": [
            "repo_id"
          ],
          "columnsTo": [
            "id"
          ],
          "onDelete": "no action",
          "onUpdate": "no action"
        }
      },
      "compositePrimaryKeys": {
        "installations_to_repos_installation_id_github_repo_id_pk": {
          "name": "installations_to_repos_installation_id_github_repo_id_pk",
          "columns": [
            "installation_id",
            "github_repo_id"
          ]
        }
      },
      "uniqueConstraints": {}
    },
    "public.installations": {
      "name": "installations",
      "schema": "",
      "columns": {
        "id": {
          "name": "id",
          "type": "text",
          "primaryKey": true,
          "notNull": true
        },
        "created_at": {
          "name": "created_at",
          "type": "timestamp (6) with time zone",
          "primaryKey": false,
          "notNull": true,
          "default": "now()"
        },
        "updated_at": {
          "name": "updated_at",
          "type": "timestamp (6) with time zone",
          "primaryKey": false,
          "notNull": true,
          "default": "now()"
        },
        "github_installation_id": {
          "name": "github_installation_id",
          "type": "bigint",
          "primaryKey": false,
          "notNull": true
        },
        "target_type": {
          "name": "target_type",
          "type": "target_type",
          "typeSchema": "public",
          "primaryKey": false,
          "notNull": true
        },
        "target_id": {
          "name": "target_id",
          "type": "text",
          "primaryKey": false,
          "notNull": true
        },
        "target_github_id": {
          "name": "target_github_id",
          "type": "bigint",
          "primaryKey": false,
          "notNull": true
        },
        "target_node_id": {
          "name": "target_node_id",
          "type": "text",
          "primaryKey": false,
          "notNull": true
        },
        "repository_selection": {
          "name": "repository_selection",
          "type": "repository_selection",
          "typeSchema": "public",
          "primaryKey": false,
          "notNull": true
        },
        "installed_by_user_id": {
          "name": "installed_by_user_id",
          "type": "text",
          "primaryKey": false,
          "notNull": true
        },
        "installed_at": {
          "name": "installed_at",
          "type": "timestamp (6) with time zone",
          "primaryKey": false,
          "notNull": true
        },
        "uninstalled_at": {
          "name": "uninstalled_at",
          "type": "timestamp (6) with time zone",
          "primaryKey": false,
          "notNull": false
        },
        "suspended_at": {
          "name": "suspended_at",
          "type": "timestamp (6) with time zone",
          "primaryKey": false,
          "notNull": false
        },
        "suspended_by": {
          "name": "suspended_by",
          "type": "text",
          "primaryKey": false,
          "notNull": false
        },
        "permissions": {
          "name": "permissions",
          "type": "jsonb",
          "primaryKey": false,
          "notNull": false
        },
        "permissions_updated_at": {
          "name": "permissions_updated_at",
          "type": "timestamp (6) with time zone",
          "primaryKey": false,
          "notNull": false
        }
      },
      "indexes": {
        "installations_target_idx": {
          "name": "installations_target_idx",
          "columns": [
            {
              "expression": "target_type",
              "isExpression": false,
              "asc": true,
              "nulls": "last"
            },
            {
              "expression": "target_id",
              "isExpression": false,
              "asc": true,
              "nulls": "last"
            }
          ],
          "isUnique": false,
          "concurrently": false,
          "method": "btree",
          "with": {}
        },
        "installations_installed_by_user_idx": {
          "name": "installations_installed_by_user_idx",
          "columns": [
            {
              "expression": "installed_by_user_id",
              "isExpression": false,
              "asc": true,
              "nulls": "last"
            }
          ],
          "isUnique": false,
          "concurrently": false,
          "method": "btree",
          "with": {}
        }
      },
      "foreignKeys": {
        "installations_installed_by_user_id_users_id_fk": {
          "name": "installations_installed_by_user_id_users_id_fk",
          "tableFrom": "installations",
          "tableTo": "users",
          "columnsFrom": [
            "installed_by_user_id"
          ],
          "columnsTo": [
            "id"
          ],
          "onDelete": "no action",
          "onUpdate": "no action"
        }
      },
      "compositePrimaryKeys": {},
      "uniqueConstraints": {
        "installations_github_installation_id_unique": {
          "name": "installations_github_installation_id_unique",
          "nullsNotDistinct": false,
          "columns": [
            "github_installation_id"
          ]
        }
      }
    },
    "public.issue_embeddings": {
      "name": "issue_embeddings",
      "schema": "",
      "columns": {
        "id": {
          "name": "id",
          "type": "text",
          "primaryKey": true,
          "notNull": true
        },
        "created_at": {
          "name": "created_at",
          "type": "timestamp (6) with time zone",
          "primaryKey": false,
          "notNull": true,
          "default": "now()"
        },
        "updated_at": {
          "name": "updated_at",
          "type": "timestamp (6) with time zone",
          "primaryKey": false,
          "notNull": true,
          "default": "now()"
        },
        "issue_id": {
          "name": "issue_id",
          "type": "text",
          "primaryKey": false,
          "notNull": true
        },
        "embedding_model": {
          "name": "embedding_model",
          "type": "text",
          "primaryKey": false,
          "notNull": false
        },
        "embedding": {
          "name": "embedding",
          "type": "vector(1536)",
          "primaryKey": false,
          "notNull": false
        },
        "embedding_generated_at": {
          "name": "embedding_generated_at",
          "type": "timestamp (6) with time zone",
          "primaryKey": false,
          "notNull": false
        },
        "issue_embedding_sync_status": {
          "name": "issue_embedding_sync_status",
          "type": "issue_embedding_sync_status",
          "typeSchema": "public",
          "primaryKey": false,
          "notNull": true,
          "default": "'ready'"
        }
      },
      "indexes": {
        "issue_embeddings_issue_id_idx": {
          "name": "issue_embeddings_issue_id_idx",
          "columns": [
            {
              "expression": "issue_id",
              "isExpression": false,
              "asc": true,
              "nulls": "last"
            }
          ],
          "isUnique": true,
          "concurrently": false,
          "method": "btree",
          "with": {}
        },
        "issue_embeddings_sync_status_idx": {
          "name": "issue_embeddings_sync_status_idx",
          "columns": [
            {
              "expression": "issue_embedding_sync_status",
              "isExpression": false,
              "asc": true,
              "nulls": "last"
            }
          ],
          "isUnique": false,
          "concurrently": false,
          "method": "btree",
          "with": {}
        },
        "issue_embeddings_embedding_idx": {
          "name": "issue_embeddings_embedding_idx",
          "columns": [
            {
              "expression": "embedding",
              "isExpression": false,
              "asc": true,
              "nulls": "last",
              "opclass": "vector_cosine_ops"
            }
          ],
          "isUnique": false,
          "concurrently": false,
          "method": "hnsw",
          "with": {}
        },
        "issue_embeddings_status_generated_at_idx": {
          "name": "issue_embeddings_status_generated_at_idx",
          "columns": [
            {
              "expression": "issue_embedding_sync_status",
              "isExpression": false,
              "asc": true,
              "nulls": "last"
            },
            {
              "expression": "embedding_generated_at",
              "isExpression": false,
              "asc": true,
              "nulls": "last"
            }
          ],
          "isUnique": false,
          "concurrently": false,
          "method": "btree",
          "with": {}
        },
        "issue_embeddings_null_idx": {
          "name": "issue_embeddings_null_idx",
          "columns": [
            {
              "expression": "issue_id",
              "isExpression": false,
              "asc": true,
              "nulls": "last"
            }
          ],
          "isUnique": false,
          "where": "embedding IS NULL",
          "concurrently": false,
          "method": "btree",
          "with": {}
        }
      },
      "foreignKeys": {
        "issue_embeddings_issue_id_issues_id_fk": {
          "name": "issue_embeddings_issue_id_issues_id_fk",
          "tableFrom": "issue_embeddings",
          "tableTo": "issues",
          "columnsFrom": [
            "issue_id"
          ],
          "columnsTo": [
            "id"
          ],
          "onDelete": "no action",
          "onUpdate": "no action"
        }
      },
      "compositePrimaryKeys": {},
      "uniqueConstraints": {}
    },
    "public.issues_to_labels": {
      "name": "issues_to_labels",
      "schema": "",
      "columns": {
        "issue_id": {
          "name": "issue_id",
          "type": "text",
          "primaryKey": false,
          "notNull": true
        },
        "label_id": {
          "name": "label_id",
          "type": "text",
          "primaryKey": false,
          "notNull": true
        },
        "created_at": {
          "name": "created_at",
          "type": "timestamp (6) with time zone",
          "primaryKey": false,
          "notNull": true,
          "default": "now()"
        },
        "updated_at": {
          "name": "updated_at",
          "type": "timestamp (6) with time zone",
          "primaryKey": false,
          "notNull": true,
          "default": "now()"
        }
      },
      "indexes": {},
      "foreignKeys": {
        "issues_to_labels_issue_id_issues_id_fk": {
          "name": "issues_to_labels_issue_id_issues_id_fk",
          "tableFrom": "issues_to_labels",
          "tableTo": "issues",
          "columnsFrom": [
            "issue_id"
          ],
          "columnsTo": [
            "id"
          ],
          "onDelete": "cascade",
          "onUpdate": "no action"
        },
        "issues_to_labels_label_id_labels_id_fk": {
          "name": "issues_to_labels_label_id_labels_id_fk",
          "tableFrom": "issues_to_labels",
          "tableTo": "labels",
          "columnsFrom": [
            "label_id"
          ],
          "columnsTo": [
            "id"
          ],
          "onDelete": "cascade",
          "onUpdate": "no action"
        }
      },
      "compositePrimaryKeys": {
        "issues_to_labels_issue_id_label_id_pk": {
          "name": "issues_to_labels_issue_id_label_id_pk",
          "columns": [
            "issue_id",
            "label_id"
          ]
        }
      },
      "uniqueConstraints": {
        "issues_to_labels_label_id_issue_id_unique": {
          "name": "issues_to_labels_label_id_issue_id_unique",
          "nullsNotDistinct": false,
          "columns": [
            "label_id",
            "issue_id"
          ]
        }
      }
    },
    "public.issues": {
      "name": "issues",
      "schema": "",
      "columns": {
        "id": {
          "name": "id",
          "type": "text",
          "primaryKey": true,
          "notNull": true
        },
        "created_at": {
          "name": "created_at",
          "type": "timestamp (6) with time zone",
          "primaryKey": false,
          "notNull": true,
          "default": "now()"
        },
        "updated_at": {
          "name": "updated_at",
          "type": "timestamp (6) with time zone",
          "primaryKey": false,
          "notNull": true,
          "default": "now()"
        },
        "repo_id": {
          "name": "repo_id",
          "type": "text",
          "primaryKey": false,
          "notNull": true
        },
        "node_id": {
          "name": "node_id",
          "type": "text",
          "primaryKey": false,
          "notNull": true
        },
        "number": {
          "name": "number",
          "type": "integer",
          "primaryKey": false,
          "notNull": true
        },
        "author": {
          "name": "author",
          "type": "jsonb",
          "primaryKey": false,
          "notNull": false
        },
        "issue_state": {
          "name": "issue_state",
          "type": "issue_state",
          "typeSchema": "public",
          "primaryKey": false,
          "notNull": true
        },
        "issue_state_reason": {
          "name": "issue_state_reason",
          "type": "issue_state_reason",
          "typeSchema": "public",
          "primaryKey": false,
          "notNull": false
        },
        "html_url": {
          "name": "html_url",
          "type": "text",
          "primaryKey": false,
          "notNull": true
        },
        "title": {
          "name": "title",
          "type": "text",
          "primaryKey": false,
          "notNull": true
        },
        "body": {
          "name": "body",
          "type": "text",
          "primaryKey": false,
          "notNull": true
        },
        "issue_created_at": {
          "name": "issue_created_at",
          "type": "timestamp (6) with time zone",
          "primaryKey": false,
          "notNull": true
        },
        "issue_updated_at": {
          "name": "issue_updated_at",
          "type": "timestamp (6) with time zone",
          "primaryKey": false,
          "notNull": true
        },
        "issue_closed_at": {
          "name": "issue_closed_at",
          "type": "timestamp (6) with time zone",
          "primaryKey": false,
          "notNull": false
        }
      },
      "indexes": {
        "repo_id_idx": {
          "name": "repo_id_idx",
          "columns": [
            {
              "expression": "repo_id",
              "isExpression": false,
              "asc": true,
              "nulls": "last"
            }
          ],
          "isUnique": false,
          "concurrently": false,
          "method": "btree",
          "with": {}
        },
        "title_substring_idx": {
          "name": "title_substring_idx",
          "columns": [
            {
              "expression": "\"title\" gin_trgm_ops",
              "asc": true,
              "isExpression": true,
              "nulls": "last"
            }
          ],
          "isUnique": false,
          "concurrently": false,
          "method": "gin",
          "with": {}
        },
        "body_substring_idx": {
          "name": "body_substring_idx",
          "columns": [
            {
              "expression": "\"body\" gin_trgm_ops",
              "asc": true,
              "isExpression": true,
              "nulls": "last"
            }
          ],
          "isUnique": false,
          "concurrently": false,
          "method": "gin",
          "with": {}
        },
        "author_name_idx": {
          "name": "author_name_idx",
          "columns": [
            {
              "expression": "lower((\"author\"->>'name'::text))",
              "asc": true,
              "isExpression": true,
              "nulls": "last"
            }
          ],
          "isUnique": false,
          "concurrently": false,
          "method": "btree",
          "with": {}
        },
        "issue_state_open_idx": {
          "name": "issue_state_open_idx",
          "columns": [
            {
              "expression": "issue_state",
              "isExpression": false,
              "asc": true,
              "nulls": "last"
            }
          ],
          "isUnique": false,
          "where": "issue_state = 'OPEN'",
          "concurrently": false,
          "method": "btree",
          "with": {}
        },
        "issue_updated_at_idx": {
          "name": "issue_updated_at_idx",
          "columns": [
            {
              "expression": "issue_updated_at",
              "isExpression": false,
              "asc": true,
              "nulls": "last"
            }
          ],
          "isUnique": false,
          "concurrently": false,
          "method": "btree",
          "with": {}
        }
      },
      "foreignKeys": {
        "issues_repo_id_repos_id_fk": {
          "name": "issues_repo_id_repos_id_fk",
          "tableFrom": "issues",
          "tableTo": "repos",
          "columnsFrom": [
            "repo_id"
          ],
          "columnsTo": [
            "id"
          ],
          "onDelete": "no action",
          "onUpdate": "no action"
        }
      },
      "compositePrimaryKeys": {},
      "uniqueConstraints": {
        "issues_node_id_unique": {
          "name": "issues_node_id_unique",
          "nullsNotDistinct": false,
          "columns": [
            "node_id"
          ]
        }
      }
    },
    "public.labels": {
      "name": "labels",
      "schema": "",
      "columns": {
        "id": {
          "name": "id",
          "type": "text",
          "primaryKey": true,
          "notNull": true
        },
        "created_at": {
          "name": "created_at",
          "type": "timestamp (6) with time zone",
          "primaryKey": false,
          "notNull": true,
          "default": "now()"
        },
        "updated_at": {
          "name": "updated_at",
          "type": "timestamp (6) with time zone",
          "primaryKey": false,
          "notNull": true,
          "default": "now()"
        },
        "node_id": {
          "name": "node_id",
          "type": "text",
          "primaryKey": false,
          "notNull": true
        },
        "name": {
          "name": "name",
          "type": "text",
          "primaryKey": false,
          "notNull": true
        },
        "color": {
          "name": "color",
          "type": "text",
          "primaryKey": false,
          "notNull": true
        },
        "description": {
          "name": "description",
          "type": "text",
          "primaryKey": false,
          "notNull": false
        }
      },
      "indexes": {},
      "foreignKeys": {},
      "compositePrimaryKeys": {},
      "uniqueConstraints": {
        "labels_node_id_unique": {
          "name": "labels_node_id_unique",
          "nullsNotDistinct": false,
          "columns": [
            "node_id"
          ]
        }
      }
    },
    "public.organizations": {
      "name": "organizations",
      "schema": "",
      "columns": {
        "id": {
          "name": "id",
          "type": "text",
          "primaryKey": true,
          "notNull": true
        },
        "created_at": {
          "name": "created_at",
          "type": "timestamp (6) with time zone",
          "primaryKey": false,
          "notNull": true,
          "default": "now()"
        },
        "updated_at": {
          "name": "updated_at",
          "type": "timestamp (6) with time zone",
          "primaryKey": false,
          "notNull": true,
          "default": "now()"
        },
        "node_id": {
          "name": "node_id",
          "type": "text",
          "primaryKey": false,
          "notNull": true
        },
        "login": {
          "name": "login",
          "type": "text",
          "primaryKey": false,
          "notNull": true
        },
        "name": {
          "name": "name",
          "type": "text",
          "primaryKey": false,
          "notNull": false
        },
        "avatar_url": {
          "name": "avatar_url",
          "type": "text",
          "primaryKey": false,
          "notNull": false
        },
        "html_url": {
          "name": "html_url",
          "type": "text",
          "primaryKey": false,
          "notNull": true
        }
      },
      "indexes": {},
      "foreignKeys": {},
      "compositePrimaryKeys": {},
      "uniqueConstraints": {
        "organizations_node_id_unique": {
          "name": "organizations_node_id_unique",
          "nullsNotDistinct": false,
          "columns": [
            "node_id"
          ]
        }
      }
    },
    "public.public_collections_to_repos": {
      "name": "public_collections_to_repos",
      "schema": "",
      "columns": {
        "collection_id": {
          "name": "collection_id",
          "type": "text",
          "primaryKey": false,
          "notNull": true
        },
        "repo_id": {
          "name": "repo_id",
          "type": "text",
          "primaryKey": false,
          "notNull": true
        },
        "created_at": {
          "name": "created_at",
          "type": "timestamp (6) with time zone",
          "primaryKey": false,
          "notNull": true,
          "default": "now()"
        },
        "updated_at": {
          "name": "updated_at",
          "type": "timestamp (6) with time zone",
          "primaryKey": false,
          "notNull": true,
          "default": "now()"
        }
      },
      "indexes": {},
      "foreignKeys": {
        "public_collections_to_repos_collection_id_public_collections_id_fk": {
          "name": "public_collections_to_repos_collection_id_public_collections_id_fk",
          "tableFrom": "public_collections_to_repos",
          "tableTo": "public_collections",
          "columnsFrom": [
            "collection_id"
          ],
          "columnsTo": [
            "id"
          ],
          "onDelete": "cascade",
          "onUpdate": "no action"
        },
        "public_collections_to_repos_repo_id_repos_id_fk": {
          "name": "public_collections_to_repos_repo_id_repos_id_fk",
          "tableFrom": "public_collections_to_repos",
          "tableTo": "repos",
          "columnsFrom": [
            "repo_id"
          ],
          "columnsTo": [
            "id"
          ],
          "onDelete": "cascade",
          "onUpdate": "no action"
        }
      },
      "compositePrimaryKeys": {
        "public_collections_to_repos_collection_id_repo_id_pk": {
          "name": "public_collections_to_repos_collection_id_repo_id_pk",
          "columns": [
            "collection_id",
            "repo_id"
          ]
        }
      },
      "uniqueConstraints": {
        "public_collections_to_repos_repo_id_collection_id_unique": {
          "name": "public_collections_to_repos_repo_id_collection_id_unique",
          "nullsNotDistinct": false,
          "columns": [
            "repo_id",
            "collection_id"
          ]
        }
      }
    },
    "public.public_collections": {
      "name": "public_collections",
      "schema": "",
      "columns": {
        "id": {
          "name": "id",
          "type": "text",
          "primaryKey": true,
          "notNull": true
        },
        "created_at": {
          "name": "created_at",
          "type": "timestamp (6) with time zone",
          "primaryKey": false,
          "notNull": true,
          "default": "now()"
        },
        "updated_at": {
          "name": "updated_at",
          "type": "timestamp (6) with time zone",
          "primaryKey": false,
          "notNull": true,
          "default": "now()"
        },
        "name": {
          "name": "name",
          "type": "text",
          "primaryKey": false,
          "notNull": true
        },
        "description": {
          "name": "description",
          "type": "text",
          "primaryKey": false,
          "notNull": false
        }
      },
      "indexes": {},
      "foreignKeys": {},
      "compositePrimaryKeys": {},
      "uniqueConstraints": {
        "public_collections_name_unique": {
          "name": "public_collections_name_unique",
          "nullsNotDistinct": false,
          "columns": [
            "name"
          ]
        }
      }
    },
    "public.repos": {
      "name": "repos",
      "schema": "",
      "columns": {
        "id": {
          "name": "id",
          "type": "text",
          "primaryKey": true,
          "notNull": true
        },
        "created_at": {
          "name": "created_at",
          "type": "timestamp (6) with time zone",
          "primaryKey": false,
          "notNull": true,
          "default": "now()"
        },
        "updated_at": {
          "name": "updated_at",
          "type": "timestamp (6) with time zone",
          "primaryKey": false,
          "notNull": true,
          "default": "now()"
        },
        "owner_login": {
          "name": "owner_login",
          "type": "text",
          "primaryKey": false,
          "notNull": true
        },
        "owner_avatar_url": {
          "name": "owner_avatar_url",
          "type": "text",
          "primaryKey": false,
          "notNull": true
        },
        "name": {
          "name": "name",
          "type": "text",
          "primaryKey": false,
          "notNull": true
        },
        "node_id": {
          "name": "node_id",
          "type": "text",
          "primaryKey": false,
          "notNull": true
        },
        "html_url": {
          "name": "html_url",
          "type": "text",
          "primaryKey": false,
          "notNull": true
        },
        "is_private": {
          "name": "is_private",
          "type": "boolean",
          "primaryKey": false,
          "notNull": true
        },
        "sync_status": {
          "name": "sync_status",
          "type": "sync_status",
          "typeSchema": "public",
          "primaryKey": false,
          "notNull": true,
          "default": "'ready'"
        },
        "last_synced_at": {
          "name": "last_synced_at",
          "type": "timestamp (6) with time zone",
          "primaryKey": false,
          "notNull": false
        },
        "init_status": {
          "name": "init_status",
          "type": "init_status",
          "typeSchema": "public",
          "primaryKey": false,
          "notNull": true,
          "default": "'ready'"
        },
        "initialized_at": {
          "name": "initialized_at",
          "type": "timestamp (6) with time zone",
          "primaryKey": false,
          "notNull": false
        },
        "issues_last_end_cursor": {
          "name": "issues_last_end_cursor",
          "type": "text",
          "primaryKey": false,
          "notNull": false
        },
        "issues_last_updated_at": {
          "name": "issues_last_updated_at",
          "type": "timestamp (6) with time zone",
          "primaryKey": false,
          "notNull": false
        }
      },
      "indexes": {
        "owner_name_idx": {
          "name": "owner_name_idx",
          "columns": [
            {
              "expression": "owner_login",
              "isExpression": false,
              "asc": true,
              "nulls": "last"
            },
            {
              "expression": "name",
              "isExpression": false,
              "asc": true,
              "nulls": "last"
            }
          ],
          "isUnique": false,
          "concurrently": false,
          "method": "btree",
          "with": {}
        },
        "owner_idx": {
          "name": "owner_idx",
          "columns": [
            {
              "expression": "owner_login",
              "isExpression": false,
              "asc": true,
              "nulls": "last"
            }
          ],
          "isUnique": false,
          "concurrently": false,
          "method": "btree",
          "with": {}
        },
        "created_at_idx": {
          "name": "created_at_idx",
          "columns": [
            {
              "expression": "created_at",
              "isExpression": false,
              "asc": true,
              "nulls": "last"
            }
          ],
          "isUnique": false,
          "concurrently": false,
          "method": "btree",
          "with": {}
        },
        "repo_sync_idx": {
          "name": "repo_sync_idx",
          "columns": [
            {
              "expression": "init_status",
              "isExpression": false,
              "asc": true,
              "nulls": "last"
            },
            {
              "expression": "sync_status",
              "isExpression": false,
              "asc": true,
              "nulls": "last"
            },
            {
              "expression": "last_synced_at",
              "isExpression": false,
              "asc": true,
              "nulls": "first"
            }
          ],
          "isUnique": false,
          "concurrently": false,
          "method": "btree",
          "with": {}
        },
        "repo_init_idx": {
          "name": "repo_init_idx",
          "columns": [
            {
              "expression": "init_status",
              "isExpression": false,
              "asc": true,
              "nulls": "last"
            },
            {
              "expression": "created_at",
              "isExpression": false,
              "asc": true,
              "nulls": "last"
            }
          ],
          "isUnique": false,
          "concurrently": false,
          "method": "btree",
          "with": {}
        }
      },
      "foreignKeys": {},
      "compositePrimaryKeys": {},
      "uniqueConstraints": {
        "repos_node_id_unique": {
          "name": "repos_node_id_unique",
          "nullsNotDistinct": false,
          "columns": [
            "node_id"
          ]
        }
      }
    },
    "public.users_to_repos": {
      "name": "users_to_repos",
      "schema": "",
      "columns": {
        "user_id": {
          "name": "user_id",
          "type": "text",
          "primaryKey": false,
          "notNull": true
        },
        "repo_id": {
          "name": "repo_id",
          "type": "text",
          "primaryKey": false,
          "notNull": true
        },
        "status": {
          "name": "status",
          "type": "subscription_status",
          "typeSchema": "public",
          "primaryKey": false,
          "notNull": true,
          "default": "'active'"
        },
        "subscribed_at": {
          "name": "subscribed_at",
          "type": "timestamp (6) with time zone",
          "primaryKey": false,
          "notNull": true,
          "default": "now()"
        },
        "unsubscribed_at": {
          "name": "unsubscribed_at",
          "type": "timestamp (6) with time zone",
          "primaryKey": false,
          "notNull": false
        },
        "created_at": {
          "name": "created_at",
          "type": "timestamp (6) with time zone",
          "primaryKey": false,
          "notNull": true,
          "default": "now()"
        },
        "updated_at": {
          "name": "updated_at",
          "type": "timestamp (6) with time zone",
          "primaryKey": false,
          "notNull": true,
          "default": "now()"
        }
      },
      "indexes": {
        "user_status_idx": {
          "name": "user_status_idx",
          "columns": [
            {
              "expression": "user_id",
              "isExpression": false,
              "asc": true,
              "nulls": "last"
            },
            {
              "expression": "status",
              "isExpression": false,
              "asc": true,
              "nulls": "last"
            },
            {
              "expression": "subscribed_at",
              "isExpression": false,
              "asc": false,
              "nulls": "last"
            }
          ],
          "isUnique": false,
          "concurrently": false,
          "method": "btree",
          "with": {}
        }
      },
      "foreignKeys": {
        "users_to_repos_user_id_users_id_fk": {
          "name": "users_to_repos_user_id_users_id_fk",
          "tableFrom": "users_to_repos",
          "tableTo": "users",
          "columnsFrom": [
            "user_id"
          ],
          "columnsTo": [
            "id"
          ],
          "onDelete": "cascade",
          "onUpdate": "no action"
        },
        "users_to_repos_repo_id_repos_id_fk": {
          "name": "users_to_repos_repo_id_repos_id_fk",
          "tableFrom": "users_to_repos",
          "tableTo": "repos",
          "columnsFrom": [
            "repo_id"
          ],
          "columnsTo": [
            "id"
          ],
          "onDelete": "cascade",
          "onUpdate": "no action"
        }
      },
      "compositePrimaryKeys": {
        "users_to_repos_user_id_repo_id_pk": {
          "name": "users_to_repos_user_id_repo_id_pk",
          "columns": [
            "user_id",
            "repo_id"
          ]
        }
      },
      "uniqueConstraints": {
        "users_to_repos_repo_id_user_id_unique": {
          "name": "users_to_repos_repo_id_user_id_unique",
          "nullsNotDistinct": false,
          "columns": [
            "repo_id",
            "user_id"
          ]
        }
      }
    },
    "public.users": {
      "name": "users",
      "schema": "",
      "columns": {
        "id": {
          "name": "id",
          "type": "text",
          "primaryKey": true,
          "notNull": true
        },
        "created_at": {
          "name": "created_at",
          "type": "timestamp (6) with time zone",
          "primaryKey": false,
          "notNull": true,
          "default": "now()"
        },
        "updated_at": {
          "name": "updated_at",
          "type": "timestamp (6) with time zone",
          "primaryKey": false,
          "notNull": true,
          "default": "now()"
        },
        "node_id": {
          "name": "node_id",
          "type": "text",
          "primaryKey": false,
          "notNull": true
        },
        "login": {
          "name": "login",
          "type": "text",
          "primaryKey": false,
          "notNull": true
        },
        "name": {
          "name": "name",
          "type": "text",
          "primaryKey": false,
          "notNull": false
        },
        "email": {
          "name": "email",
          "type": "text",
          "primaryKey": false,
          "notNull": true
        },
        "avatar_url": {
          "name": "avatar_url",
          "type": "text",
          "primaryKey": false,
          "notNull": false
        },
        "html_url": {
          "name": "html_url",
          "type": "text",
          "primaryKey": false,
          "notNull": true
        },
        "github_scopes": {
          "name": "github_scopes",
          "type": "jsonb",
          "primaryKey": false,
          "notNull": false
        },
        "auth_revoked_at": {
          "name": "auth_revoked_at",
          "type": "timestamp (6) with time zone",
          "primaryKey": false,
          "notNull": false
        },
        "access_token": {
          "name": "access_token",
          "type": "text",
          "primaryKey": false,
          "notNull": true
        },
        "metadata": {
          "name": "metadata",
          "type": "jsonb",
          "primaryKey": false,
          "notNull": false
        }
      },
      "indexes": {},
      "foreignKeys": {},
      "compositePrimaryKeys": {},
      "uniqueConstraints": {
        "users_node_id_unique": {
          "name": "users_node_id_unique",
          "nullsNotDistinct": false,
          "columns": [
            "node_id"
          ]
        }
      }
    }
  },
  "enums": {
    "public.repository_selection": {
      "name": "repository_selection",
      "schema": "public",
      "values": [
        "all",
        "selected"
      ]
    },
    "public.target_type": {
      "name": "target_type",
      "schema": "public",
      "values": [
        "user",
        "organization"
      ]
    },
    "public.issue_embedding_sync_status": {
      "name": "issue_embedding_sync_status",
      "schema": "public",
      "values": [
        "ready",
        "in_progress",
        "error"
      ]
    },
    "public.issue_state": {
      "name": "issue_state",
      "schema": "public",
      "values": [
        "OPEN",
        "CLOSED"
      ]
    },
    "public.issue_state_reason": {
      "name": "issue_state_reason",
      "schema": "public",
      "values": [
        "COMPLETED",
        "REOPENED",
        "NOT_PLANNED",
        "DUPLICATE"
      ]
    },
    "public.init_status": {
      "name": "init_status",
      "schema": "public",
      "values": [
        "pending",
        "ready",
        "in_progress",
        "completed",
        "error"
      ]
    },
    "public.sync_status": {
      "name": "sync_status",
      "schema": "public",
      "values": [
        "ready",
        "queued",
        "in_progress",
        "error"
      ]
    },
    "public.subscription_status": {
      "name": "subscription_status",
      "schema": "public",
      "values": [
        "active",
        "inactive"
      ]
    }
  },
  "schemas": {},
  "sequences": {},
  "_meta": {
    "columns": {},
    "schemas": {},
    "tables": {}
  }
}